examples/cherrypy_example.py
examples/controller_example.py
examples/exception_example.py
examples/gpiod_example.py
examples/simple_example.py
examples/tkinter_example.py
examples/todo_filereader.py
examples/templates/base.html
examples/templates/index.html
examples/templates/login.html
examples/templates/part_header.html
examples/webroot/static/favicon.ico
examples/webroot/static/logo.png
examples/webroot/static/styles.css
looselycoupled/__init__.py
looselycoupled/cmdqueue.py
looselycoupled/configuration.py
looselycoupled/eventloop.py
looselycoupled/metadata.py
looselycoupled/mock_gpiod.py
looselycoupled/mock_prometheus.py
looselycoupled/module.py
looselycoupled/module_clickhandler.py
looselycoupled/module_gpiod.py
looselycoupled/module_prometheus.py
looselycoupled/module_threaded.py
looselycoupled/modulemanager.py
looselycoupled/monitoredthreadpoolexecutor.py
looselycoupled-0.6.1.dist-info/licenses/LICENSE
looselycoupled-0.6.1.dist-info/METADATA
looselycoupled-0.6.1.dist-info/WHEEL
looselycoupled-0.6.1.dist-info/entry_points.txt
looselycoupled-0.6.1.dist-info/top_level.txt
looselycoupled-0.6.1.dist-info/RECORD
