Metadata-Version: 2.4
Name: looselycoupled
Version: 0.6.1
Summary: simplistic asyncio-based framework for loosely coupling application modules that can interact synchronously and asynchronously (event queue)
Home-page: https://www.github.com/towalink/looselycoupled
Author: Dirk Henrici
Author-email: towalink.looselycoupled@henrici.name
License: AGPL-3.0-or-later
Project-URL: Project homepage, https://www.github.com/towalink/looselycoupled
Project-URL: Repository, https://www.github.com/towalink/looselycoupled
Project-URL: PyPi, https://pypi.org/project/looselycoupled/
Keywords: event-driven asynchronous asyncio messaging
Classifier: Programming Language :: Python
Classifier: Programming Language :: Python :: 3
Classifier: Operating System :: POSIX :: Linux
Classifier: Development Status :: 4 - Beta
Classifier: Intended Audience :: Developers
Classifier: Intended Audience :: Information Technology
Requires-Python: >=3.8
License-File: LICENSE
Requires-Dist: pyyaml
Provides-Extra: webserver
Requires-Dist: cherrypy; extra == "webserver"
Requires-Dist: jinja2; extra == "webserver"
Provides-Extra: prometheus
Requires-Dist: prometheus-client; extra == "prometheus"
Dynamic: author
Dynamic: author-email
Dynamic: classifier
Dynamic: description
Dynamic: description-content-type
Dynamic: home-page
Dynamic: keywords
Dynamic: license
Dynamic: license-file
Dynamic: project-url
Dynamic: provides-extra
Dynamic: requires-dist
Dynamic: requires-python
Dynamic: summary
